[  
      {
        "nombres": "Andrés Mauricio",
        "apellidos": "Cortés Rodríguez ",
        "nacimiento": "03/02/1997 ",
        "suscripcion": "05/03/2019 ",
        "pais": "Honduras "
      },
      {
        "nombres": "Yi",
        "apellidos": "Jie Feng",
        "nacimiento": "13/07/1995",
        "suscripcion": "18/05/2019",
        "pais": "China"
      },
      {
        "nombres": "María",
        "apellidos": "Belén Gallo",
        "nacimiento": "19/20/1990",
        "suscripcion": "25/09/2019",
        "pais": "Perú"
      },
      {
        "nombres": "Ophelie",
        "apellidos": "Masson Guillot",
        "nacimiento": "25/04/2003",
        "suscripcion": "16/11/2019",
        "pais": "Francia"
      },
      {
        "nombres": "Abhijeet",
        "apellidos": "Aarti Gadhavi",
        "nacimiento": "30/12/2000",
        "suscripcion": "24/02/2020",
        "pais": "India"
      },
      {
        "nombres": "Pedrinho Haroldo",
        "apellidos": "Madeira Abel",
        "nacimiento": "20/07/1996",
        "suscripcion": "15/05/2020",
        "pais": "Brasil"
      },
      {
        "nombres": "Bushra",
        "apellidos": "Hafsah Ahmad",
        "nacimiento": "04/10/2002",
        "suscripcion": "23/08/2020",
        "pais": "Egipto"
      },
      {
        "nombres": "Dua",
        "apellidos": "Hilal Abbas",
        "nacimiento": "06/11/1998",
        "suscripcion": "12/09/2020",
        "pais": "Etiopía"
      },
      {
        "nombres": "Salma Faris",
        "apellidos": "Najjar Qadir",
        "nacimiento": "23/02/1995",
        "suscripcion": "03/01/2021",
        "pais": "Israel"
      },
      {
        "nombres": "Ramesh",
        "apellidos": "Kumar Anand",
        "nacimiento": "01/01/2001",
        "suscripcion": "19/06/2021",
        "pais": "India"
      } 
    ]